pssmgen/__init__.py
pssmgen/__version__.py
pssmgen/map_pssm2pdb.py
pssmgen/pssm.py
PSSMGen-0.1.2.dist-info/LICENSE
PSSMGen-0.1.2.dist-info/METADATA
PSSMGen-0.1.2.dist-info/WHEEL
PSSMGen-0.1.2.dist-info/top_level.txt
PSSMGen-0.1.2.dist-info/RECORD
