Metadata-Version: 2.1
Name: PSSMGen
Version: 0.1.2
Summary: Generates consistent PSSM and/or PDB files for protein-protein complexes
Home-page: https://github.com/DeepRank/PSSMGen
Author: Nicolas Renaud, Cunliang Geng
Author-email: n.renaud@esciencecenter.nl, c.geng@esciencecenter.nl
License: Apache Software License 2.0
Keywords: pssmgen
Platform: UNKNOWN
Requires-Dist: numpy (>=1.13)
Requires-Dist: scipy
Requires-Dist: biopython
Requires-Dist: pdb2sql (>=0.5)
Provides-Extra: test
Requires-Dist: nose ; extra == 'test'
Requires-Dist: coverage ; extra == 'test'
Requires-Dist: pytest ; extra == 'test'
Requires-Dist: pytest-cov ; extra == 'test'
Requires-Dist: codacy-coverage ; extra == 'test'
Requires-Dist: coveralls ; extra == 'test'
